LICENSE
MANIFEST.in
README.md
setup.py
tap_ujet/__init__.py
tap_ujet/client.py
tap_ujet/discover.py
tap_ujet/schema.py
tap_ujet/streams.py
tap_ujet/sync.py
tap_ujet/transform.py
tap_ujet.egg-info/PKG-INFO
tap_ujet.egg-info/SOURCES.txt
tap_ujet.egg-info/dependency_links.txt
tap_ujet.egg-info/entry_points.txt
tap_ujet.egg-info/requires.txt
tap_ujet.egg-info/top_level.txt
tap_ujet/schemas/agent_activity_logs.json
tap_ujet/schemas/agents.json
tap_ujet/schemas/calls.json
tap_ujet/schemas/chats.json
tap_ujet/schemas/menu_tree.json
tap_ujet/schemas/menus.json
tap_ujet/schemas/team_tree.json
tap_ujet/schemas/teams.json
tap_ujet/schemas/user_statuses.json