Metadata-Version: 2.1
Name: tap-ujet
Version: 0.0.3
Summary: Singer.io tap for extracting data from the UJET API
Home-page: UNKNOWN
Author: jeff.huth@bytecode.io
License: UNKNOWN
Platform: UNKNOWN
Classifier: Programming Language :: Python :: 3 :: Only
Provides-Extra: dev
